[{"_path":"/architecture","_dir":"","_draft":false,"_partial":false,"_locale":"","_empty":false,"title":"Architecture","description":"The whole tradeb0t project is divided into several layers:","_type":"markdown","_id":"content:2.architecture.md","_source":"content","_file":"2.architecture.md","_extension":"md"},{"_path":"/algorithms/overview","_dir":"algorithms","_draft":false,"_partial":false,"_locale":"","_empty":false,"title":"Overview","description":"Tradeb0t provides abstract classes for trading algorithms. It is designed to make it possible to reuse the same code for different exchanges.","_type":"markdown","_id":"content:4.algorithms:1.overview.md","_source":"content","_file":"4.algorithms/1.overview.md","_extension":"md"}]